mygeopackage/__init__.py
mygeopackage/mygeopackage.py
mygeopackage/pproc.py
mygeopackage/regression.py
mygeopackage/toolbar.py
mygeopackage/unsupervised.py
mygeopackage/utility.py
mygeopackage-0.1.5.dist-info/LICENSE
mygeopackage-0.1.5.dist-info/METADATA
mygeopackage-0.1.5.dist-info/WHEEL
mygeopackage-0.1.5.dist-info/dependency_links.txt
mygeopackage-0.1.5.dist-info/top_level.txt
mygeopackage-0.1.5.dist-info/RECORD
