Metadata-Version: 2.1
Name: mygeopackage
Version: 0.1.5
Summary: Python package for gis application
Home-page: https://github.com/yungming0119/mygeopackage
Author: Yung-Ming Tsai
Author-email: ytsai5@vols.utk.edu
License: MIT license
Keywords: mygeopackage
Platform: UNKNOWN
Classifier: Development Status :: 2 - Pre-Alpha
Classifier: Intended Audience :: Developers
Classifier: License :: OSI Approved :: MIT License
Classifier: Natural Language :: English
Classifier: Programming Language :: Python :: 3
Classifier: Programming Language :: Python :: 3.5
Classifier: Programming Language :: Python :: 3.6
Classifier: Programming Language :: Python :: 3.7
Classifier: Programming Language :: Python :: 3.8
Requires-Python: >=3.5
Requires-Dist: numpy
Requires-Dist: scikit-learn
Requires-Dist: ipyleaflet
Requires-Dist: folium
Requires-Dist: pyshp
Requires-Dist: whitebox
Requires-Dist: ipyfilechooser
